Metadata-Version: 1.0
Name: estimators-efb
Version: 0.3
Summary: Customized estimators
Home-page: UNKNOWN
Author: Everton Bin
Author-email: everton.bin@gmail.com
License: UNKNOWN
Platform: UNKNOWN
